setup.py
sonm/__init__.py
sonm/bid.py
sonm/consts.py
sonm/customer.py
sonm/deal.py
sonm/order.py
sonm/task.py
sonm.egg-info/PKG-INFO
sonm.egg-info/SOURCES.txt
sonm.egg-info/dependency_links.txt
sonm.egg-info/requires.txt
sonm.egg-info/top_level.txt
sonm/templates/bid.jinja2
sonm/templates/task.jinja2