Metadata-Version: 1.0
Name: sonm
Version: 0.0.6
Summary: Wrapper for SONM API https://github.com/sonm-io
Home-page: https://github.com/telminov/sonm
Author: Telminov Sergey
Author-email: sergey@telminov.ru
License: The MIT License
Platform: UNKNOWN
